pyMFDR/__init__.py
pyMFDR/archetypes.py
pyMFDR/lae.py
pyMFDR/mfdr.py
pyMFDR/pca.py
pyMFDR-0.1.5.dist-info/LICENCE
pyMFDR-0.1.5.dist-info/METADATA
pyMFDR-0.1.5.dist-info/WHEEL
pyMFDR-0.1.5.dist-info/top_level.txt
pyMFDR-0.1.5.dist-info/RECORD
